[{"datum":"2020-10-29","lokacije":[{"lokacija":"Eishalle Gröden","liga":"AHL","sodniki":[{"ime":"MOSCHEN"},{"ime":"PINIE"},{"ime":"DE ZORDO"},{"ime":"FLEISCHMANN"}]}]},{"datum":"2020-10-30","lokacije":[{"lokacija":"Eisarena Salzburg","liga":"AHL","sodniki":[{"ime":"BRUNNER"},{"ime":"KUMMER"},{"ime":"MATTHEY"},{"ime":"REISINGER"},{"ime":"VEIT"}]}]},{"datum":"2020-10-31","lokacije":[{"lokacija":"Eishalle Jesenice","liga":"AHL","sodniki":[{"ime":"PAHOR"},{"ime":"REZEK"},{"ime":"PAGON"},{"ime":"SNOJ"},{"ime":"PAHOR"}]},{"lokacija":"Eishalle Sterzing","liga":"AHL","sodniki":[{"ime":"EGGER"},{"ime":"STEFENELLI"},{"ime":"CRISTELI"},{"ime":"DE ZORDO"}]},{"lokacija":"Sportpark Kitzbühel","liga":"AHL","sodniki":[{"ime":"HEINRICHER"},{"ime":"WIDMANN"},{"ime":"EISL"},{"ime":"HUBER"}]},{"lokacija":"Eishalle Bruneck","liga":"AHL","sodniki":[{"ime":"GIACOMOZZI"},{"ime":"LAZZERI"},{"ime":"FLEISCHMANN"},{"ime":"PIRAS"}]}]},{"datum":"2020-11-01","lokacije":[{"lokacija":"Klagenfurter Stadthalle","liga":"AHL","sodniki":[{"ime":"OREL"},{"ime":"PODLESNIK"},{"ime":"PÖTSCHER"},{"ime":"SCHWEIGHOFER"}]},{"lokacija":"Eishalle Jesenice","liga":"AHL","sodniki":[{"ime":"FAJDIGA"},{"ime":"LESNIAK"},{"ime":"ARLIC"},{"ime":"JAVORNIK"}]}]}]